aiostate/__init__.py
aiostate-0.1.0.dist-info/LICENSE
aiostate-0.1.0.dist-info/METADATA
aiostate-0.1.0.dist-info/WHEEL
aiostate-0.1.0.dist-info/RECORD
