Metadata-Version: 2.3
Name: aiostate
Version: 0.1.0
Summary: A flexible, async-friendly state machine implementation for Python with thread-safe operations and decorator-based transitions.
License: MIT License
Keywords: asyncio,state-machine,fsm,python,async,state
Author: BoChen SHEN
Author-email: 6goddddddd@gmail.com
Requires-Python: >=3.11,<3.13
Classifier: License :: OSI Approved :: MIT License
Classifier: Programming Language :: Python :: 3
Classifier: Programming Language :: Python :: 3.11
Classifier: Programming Language :: Python :: 3.12
Classifier: Topic :: Software Development :: Libraries
Classifier: Operating System :: OS Independent
Classifier: Framework :: AsyncIO
